tom_swift/__init__.py
tom_swift/swift.py
tom_swift/swift_api.py
tom_swift/templates/tom_swift/observation_form.html
tom_swift/test_swift.py
tom_swift-0.3.1.dist-info/LICENSE
tom_swift-0.3.1.dist-info/METADATA
tom_swift-0.3.1.dist-info/WHEEL
tom_swift-0.3.1.dist-info/RECORD
