Metadata-Version: 2.1
Name: tom-swift
Version: 0.3.1
Summary: TOM Toolkit Facility module for the Neil Gehrels Swift Observatory
License: GPL-3.0-or-later
Author: Lindy Lindstrom
Author-email: llindstrom@lco.global
Requires-Python: >=3.8.1,<3.12
Classifier: License :: OSI Approved :: GNU General Public License v3 or later (GPLv3+)
Classifier: Programming Language :: Python :: 3
Classifier: Programming Language :: Python :: 3.9
Classifier: Programming Language :: Python :: 3.10
Classifier: Programming Language :: Python :: 3.11
Requires-Dist: boto3 (>=1.34.136,<2.0.0)
Requires-Dist: swifttools (<4)
Requires-Dist: tomtoolkit (>=2.15)
